nanograd_bgriebel/_core.cpython-313-darwin.so
nanograd_bgriebel/__init__.py
nanograd_bgriebel/_core/__init__.pyi
nanograd_bgriebel/_core/nn.pyi
nanograd_bgriebel/_core/engine.pyi
nanograd_bgriebel-0.1.4.dist-info/RECORD
nanograd_bgriebel-0.1.4.dist-info/WHEEL
nanograd_bgriebel-0.1.4.dist-info/METADATA
nanograd_bgriebel-0.1.4.dist-info/licenses/LICENSE
