Metadata-Version: 2.1
Name: nanograd-bgriebel
Version: 0.1.4
Summary: Scalar Automatic Differentiation Engine
Keywords: Automatic Differentiation,Neural Network,Machine Learning
Author-Email: Braden Griebel <bgriebel@uw.edu>
License: Copyright 2025 Braden Griebel
Classifier: Development Status :: 3 - Alpha
Classifier: Programming Language :: Python :: 3.10
Classifier: Programming Language :: Python :: 3.11
Classifier: Programming Language :: Python :: 3.12
Classifier: Programming Language :: Python :: 3.13
Project-URL: Homepage, https://github.com/Braden-Griebel/nanograd
Project-URL: Repository, https://github.com/Braden-Griebel/nanograd
Project-URL: Issues, https://github.com/Braden-Griebel/nanograd/issues
Project-URL: Documentation, https://nanograd.readthedocs.io/en/latest/
Requires-Python: >=3.10
